Secr/__init__.py
Secr/logs.py
Secr/secrmath.py
SecrLib-0.0.4.dist-info/LICENSE
SecrLib-0.0.4.dist-info/METADATA
SecrLib-0.0.4.dist-info/WHEEL
SecrLib-0.0.4.dist-info/top_level.txt
SecrLib-0.0.4.dist-info/RECORD
