Metadata-Version: 2.1
Name: SecrLib
Version: 0.0.4
Summary: A python library made by SecretaSoftworks
Home-page: https://github.com/Dauby/SecrLib
Author: SecretaSoftworks
Author-email: fidesindeumetvirtus@gmail.com
License: UNKNOWN
Project-URL: Bug Tracker, https://github.com/Dauby/SecrLib/issues
Platform: UNKNOWN
Classifier: Programming Language :: Python :: 3
Classifier: License :: OSI Approved :: MIT License
Classifier: Operating System :: OS Independent
Requires-Python: >=3.6
License-File: LICENSE
